pycccedict/cccedict.py
pycccedict/cccedict_test.py
pycccedict/data/cedict_1_0_ts_utf-8_mdbg.txt.gz
pycccedict-1.1.0.dist-info/LICENSE.txt
pycccedict-1.1.0.dist-info/METADATA
pycccedict-1.1.0.dist-info/WHEEL
pycccedict-1.1.0.dist-info/RECORD
