Metadata-Version: 2.1
Name: pycccedict
Version: 1.1.0
Summary: CC-CEDIT in Python
Home-page: https://github.com/patrickpei/pycccedict
License: CC BY-SA 4.0
Author: Patrick Pei
Author-email: 14530807+patrickpei@users.noreply.github.com
Requires-Python: >=3.8,<4.0
Classifier: License :: Other/Proprietary License
Classifier: Programming Language :: Python :: 3
Classifier: Programming Language :: Python :: 3.8
Classifier: Programming Language :: Python :: 3.9
Classifier: Programming Language :: Python :: 3.10
Classifier: Programming Language :: Python :: 3.11
Project-URL: Documentation, https://github.com/patrickpei/pycccedict#api
Project-URL: Repository, https://github.com/patrickpei/pycccedict
